opencv/fr/__init__.py
opencv/fr/api_error.py
opencv/fr/http_interactor.py
opencv/fr/schemas.py
opencv/fr/sdk.py
opencv/fr/util.py
opencv/fr/collections/collections_manager.py
opencv/fr/collections/schemas.py
opencv/fr/compare/compare_manager.py
opencv/fr/compare/schemas.py
opencv/fr/liveness/liveness_manager.py
opencv/fr/liveness/schemas.py
opencv/fr/persons/persons_manager.py
opencv/fr/persons/schemas.py
opencv/fr/search/schemas.py
opencv/fr/search/search_manager.py
opencv_face_recognition-1.1.1.dist-info/LICENSE
opencv_face_recognition-1.1.1.dist-info/METADATA
opencv_face_recognition-1.1.1.dist-info/WHEEL
opencv_face_recognition-1.1.1.dist-info/top_level.txt
opencv_face_recognition-1.1.1.dist-info/RECORD
