Metadata-Version: 2.1
Name: opencv-face-recognition
Version: 1.1.1
Summary: Revolutionize Biometric Authentication with OpenCV Face Recognition: Top-Rated Accuracy & Liveness Detection
Author-email: Seventh Sense Artificial Intelligence Private Limited <support@seventhsense.ai>
License: The MIT License (MIT)
Project-URL: Homepage, https://docs.opencv.fr/python
Keywords: Opencv Face Recognition,Opencv FR,Face Verification,Face Recognition
Classifier: License :: OSI Approved :: MIT License
Classifier: Programming Language :: Python
Classifier: Programming Language :: Python :: 3
Requires-Python: >=3.6
License-File: LICENSE
Requires-Dist: numpy
Requires-Dist: opencv-python
Requires-Dist: pillow
Requires-Dist: python-dateutil
Requires-Dist: requests
Provides-Extra: dev
Requires-Dist: mkdocs; extra == "dev"
